minimus/__init__.py
minimus/__main__.py
minimus/src/__init__.py
minimus/src/constants.py
minimus/src/markup.py
minimus/src/objects.py
minimus/src/output.py
minimus/src/storage.py
minimus/src/utils.py
minimus-2.0.1.dist-info/LICENSE.txt
minimus-2.0.1.dist-info/METADATA
minimus-2.0.1.dist-info/WHEEL
minimus-2.0.1.dist-info/entry_points.txt
minimus-2.0.1.dist-info/top_level.txt
minimus-2.0.1.dist-info/RECORD
