Metadata-Version: 2.1
Name: minimus
Version: 2.0.1
Summary: Personal knowledge storage formatter
Author-email: Igor Zyktin <nicord@yandex.ru>
Project-URL: Homepage, https://github.com/IgorZyktin/minimus
Classifier: Programming Language :: Python :: 3
Classifier: License :: OSI Approved :: MIT License
Classifier: Operating System :: OS Independent
Requires-Python: >=3.10
License-File: LICENSE.txt
